{
    "user_antigo":{
        "nome": "Nome Antigo",
        "email": "emailantigo@email.com",
        "password": "teste",
        "administrador": "true"  
    },
    "nome_novo":{
        "nome": "Nome Novo",
        "email": "emailantigo@email.com",
        "password": "teste",
        "administrador": "true"
    },
    "user_invalido":{
        "nome": "Invalido Tester",
        "email": "fulano@qa.com",
        "password": "teste",
        "administrador": "true"
    },
    "user_nao_admin":{
        "nome": "Não Admin",
        "email": "nsouadmin@email.com",
        "password": "teste",
        "administrador": "false"
    }
}